{
  "project_info": {
    "project_number": "40341497718",
    "project_id": "cs443termproject",
    "storage_bucket": "cs443termproject.appspot.com"
  },
  "client": [
    {
      "client_info": {
        "mobilesdk_app_id": "1:40341497718:android:41ead475c966ce5fa23c57",
        "android_client_info": {
          "package_name": "edu.umb.cs443termproject"
        }
      },
      "oauth_client": [
        {
          "client_id": "40341497718-esd2jhuj6escnejm48t3crtvpcr16d9j.apps.googleusercontent.com",
          "client_type": 3
        }
      ],
      "api_key": [
        {
          "current_key": "AIzaSyB-QsBOuocVXfdPmtwn6DIRFQvs0MUravE"
        }
      ],
      "services": {
        "appinvite_service": {
          "other_platform_oauth_client": [
            {
              "client_id": "40341497718-esd2jhuj6escnejm48t3crtvpcr16d9j.apps.googleusercontent.com",
              "client_type": 3
            }
          ]
        }
      }
    }
  ],
  "configuration_version": "1"
}